taxii2client/__init__.py
taxii2client/common.py
taxii2client/exceptions.py
taxii2client/version.py
taxii2client/v20/__init__.py
taxii2client/v21/__init__.py
taxii2_client-2.3.0.dist-info/LICENSE
taxii2_client-2.3.0.dist-info/METADATA
taxii2_client-2.3.0.dist-info/WHEEL
taxii2_client-2.3.0.dist-info/top_level.txt
taxii2_client-2.3.0.dist-info/RECORD
