Metadata-Version: 2.1
Name: taxii2-client
Version: 2.3.0
Summary: TAXII 2 Client Library
Home-page: https://oasis-open.github.io/cti-documentation/
Author: OASIS Cyber Threat Intelligence Technical Committee
Author-email: cti-users@lists.oasis-open.org
Maintainer: Emmanuelle Vargas-Gonzalez
Maintainer-email: emmanuelle@mitre.org
License: BSD
Project-URL: Source Code, https://github.com/oasis-open/cti-taxii-client/
Project-URL: Documentation, https://taxii2client.readthedocs.io/
Project-URL: Bug Tracker, https://github.com/oasis-open/cti-taxii-client/issues/
Keywords: taxii taxii2 client json cti cyber threat intelligence
Platform: UNKNOWN
Classifier: Development Status :: 3 - Alpha
Classifier: Intended Audience :: Developers
Classifier: Topic :: Security
Classifier: License :: OSI Approved :: BSD License
Classifier: Programming Language :: Python :: 3
Classifier: Programming Language :: Python :: 3.6
Classifier: Programming Language :: Python :: 3.7
Classifier: Programming Language :: Python :: 3.8
Classifier: Programming Language :: Python :: 3.9
Provides-Extra: test
Provides-Extra: docs
